{
  "version": "1.1.0",
  "diagrams": [
    {
      "ordinal": 0,
      "scrollPosition": {
        "x": 206.99325046032607,
        "y": 0
      },
      "nodes": [
        {
          "location": {
            "x": 360.81043207274951,
            "y": 470.93350967084666
          },
          "nodeIndex": "dim_date_fiscal_DateKey",
          "nodeLineageTag": "6283fb61-df62-4f0a-b20b-b6080992292e",
          "size": {
            "height": 300,
            "width": 234
          },
          "zIndex": 1
        },
        {
          "location": {
            "x": 597.27823415269654,
            "y": 877.90908707071912
          },
          "nodeIndex": "dim_date_fiscal_MonthKey",
          "nodeLineageTag": "f85aa0b1-de4c-4ac4-a54e-d8cbac7e3a9f",
          "size": {
            "height": 300,
            "width": 234
          },
          "zIndex": 5
        },
        {
          "location": {
            "x": 14.697456997264453,
            "y": 383.7261939904908
          },
          "nodeIndex": "dim_date_fiscal_TTMKey",
          "nodeLineageTag": "688cf5f7-ded9-4474-8a63-e279ff1650b9",
          "size": {
            "height": 128,
            "width": 234
          },
          "zIndex": 2
        },
        {
          "location": {
            "x": 803.13589409456335,
            "y": 288.05784752129387
          },
          "nodeIndex": "fact_myPayRequestReport_Sharepoint",
          "nodeLineageTag": "a77d6c7f-e35c-40de-aa09-f65615cc13af",
          "size": {
            "height": 300,
            "width": 234
          },
          "zIndex": 0
        },
        {
          "location": {
            "x": 33.236691802397218,
            "y": 893.46571398714468
          },
          "nodeIndex": ".Measures",
          "nodeLineageTag": "00ef07bf-7e7f-437a-887d-c83864fc2b65",
          "size": {
            "height": 128,
            "width": 234
          },
          "zIndex": 0
        },
        {
          "location": {
            "x": 1027.6797331810219,
            "y": 1094.879984795406
          },
          "nodeIndex": "dim_gbs_mor_Goals",
          "nodeLineageTag": "4468c842-3c74-4e19-86a5-ede1f30f093b",
          "size": {
            "height": 300,
            "width": 234
          },
          "zIndex": 0
        },
        {
          "location": {
            "x": 20.181448112714179,
            "y": 177.62373351527032
          },
          "nodeIndex": "dim_date_Holiday",
          "nodeLineageTag": "86c3c1c3-09db-4e77-9337-a11ea2060ae1",
          "size": {
            "height": 152,
            "width": 234
          },
          "zIndex": 0
        },
        {
          "location": {
            "x": 1447.9349900966354,
            "y": 154.11911393211233
          },
          "nodeIndex": "dim_Employee_Payroll",
          "nodeLineageTag": "89f7e953-c2ef-4ee4-abea-bdc1fcd4ad0a",
          "size": {
            "height": 296,
            "width": 234
          },
          "zIndex": 0
        },
        {
          "location": {
            "x": 1129.3164368071084,
            "y": 583.38129416873232
          },
          "nodeIndex": "fact_ManualCheckRequest_Payroll",
          "nodeLineageTag": "166fbd19-6174-4731-a686-4f6232f81fb7",
          "size": {
            "height": 300,
            "width": 234
          },
          "zIndex": 0
        }
      ],
      "name": "All tables",
      "zoomValue": 50.346892102823091,
      "pinKeyFieldsToTop": false,
      "showExtraHeaderInfo": false,
      "hideKeyFieldsWhenCollapsed": false,
      "tablesLocked": false
    }
  ],
  "selectedDiagram": "All tables",
  "defaultDiagram": "All tables"
}